silhouette/__init__.py
silhouette/abi/silhouette.json
silhouette/api/__init__.py
silhouette/api/auth.py
silhouette/api/client.py
silhouette/hyperliquid/__init__.py
silhouette/hyperliquid/api.py
silhouette/hyperliquid/exchange.py
silhouette/hyperliquid/info.py
silhouette/hyperliquid/utils/__init__.py
silhouette/hyperliquid/utils/constants.py
silhouette/hyperliquid/utils/error.py
silhouette/hyperliquid/utils/signing.py
silhouette/hyperliquid/utils/types.py
silhouette/hyperliquid/websocket_manager.py
silhouette/py.typed
silhouette/utils/__init__.py
silhouette/utils/conversions.py
silhouette/utils/types.py
silhouette_python_sdk-0.1.0.dist-info/LICENSE.md
silhouette_python_sdk-0.1.0.dist-info/METADATA
silhouette_python_sdk-0.1.0.dist-info/WHEEL
silhouette_python_sdk-0.1.0.dist-info/RECORD
