Metadata-Version: 2.3
Name: silhouette-python-sdk
Version: 0.1.0
Summary: Python SDK for trading on Silhouette - the shield exchange on Hyperliquid
License: MIT
Keywords: silhouette,trading,privacy,exchange,hyperliquid,defi,crypto,sdk
Author: Silhouette
Author-email: aidan@silhouette.exchange
Requires-Python: >=3.10,<4
Classifier: Development Status :: 3 - Alpha
Classifier: Intended Audience :: Developers
Classifier: Operating System :: OS Independent
Classifier: Topic :: Software Development :: Libraries :: Python Modules
Classifier: License :: OSI Approved :: MIT License
Classifier: Programming Language :: Python :: 3
Classifier: Programming Language :: Python :: 3.10
Classifier: Programming Language :: Python :: 3.11
Classifier: Programming Language :: Python :: 3.12
Classifier: Programming Language :: Python :: 3.13
Requires-Dist: hyperliquid-python-sdk (>=0.20.0,<1.0.0)
Requires-Dist: requests (>=2.32.3,<3.0.0)
Requires-Dist: siwe (>=4.4.0,<5.0.0)
Requires-Dist: typing_extensions (>=4.9.0) ; python_version < "3.11"
Project-URL: Homepage, https://github.com/silhouette-exchange/silhouette-python-sdk
Project-URL: Repository, https://github.com/silhouette-exchange/silhouette-python-sdk
